rabbitplay.py
setup.cfg
setup.py
RabbitPlay.egg-info/PKG-INFO
RabbitPlay.egg-info/SOURCES.txt
RabbitPlay.egg-info/dependency_links.txt
RabbitPlay.egg-info/requires.txt
RabbitPlay.egg-info/top_level.txt