Metadata-Version: 1.1
Name: RabbitPlay
Version: 0.7.1
Summary: Abstraction on top of pika for working with RabbitMQ.
Home-page: https://github.com/SwipeBank/rabbitplay
Author: Eugene <f0t0n> Naydenov, Michael <m1kev> Voropaiev
Author-email: t.34.oxygen@gmail.com, m.voropaiev@gmail.com
License: UNKNOWN
Download-URL: https://github.com/SwipeBank/rabbitplay/archive/0.7.1.tar.gz
Platform: UNKNOWN
